bench_wizard/__init__.py
bench_wizard/__main__.py
bench_wizard/__version__.py
bench_wizard/benchmark.py
bench_wizard/cargo.py
bench_wizard/db_bench.py
bench_wizard/exceptions.py
bench_wizard/main.py
bench_wizard/output.py
bench_wizard/parser.py
bench_wizard/performance.py
bench_wizard-0.5.2.dist-info/entry_points.txt
bench_wizard-0.5.2.dist-info/LICENSE
bench_wizard-0.5.2.dist-info/WHEEL
bench_wizard-0.5.2.dist-info/METADATA
bench_wizard-0.5.2.dist-info/RECORD
