Metadata-Version: 2.1
Name: bench-wizard
Version: 0.5.2
Summary: 
Author: Martin Hloska
Author-email: martin.hloska@gmail.com
Requires-Python: >=3.8,<4.0
Classifier: Programming Language :: Python :: 3
Classifier: Programming Language :: Python :: 3.10
Classifier: Programming Language :: Python :: 3.8
Classifier: Programming Language :: Python :: 3.9
Requires-Dist: click (>=7.1.2,<8.0.0)
